{
  "doc_id": "2602.23831v1.pdf",
  "title": "Antenna Coding Optimization for Pixel Antenna Empowered Wireless Communication Using Deep Learning with Heterogeneous Multi-Head Selection",
  "abstract": "—Pixel antenna is a promising antenna technology that enables flexible adjustment of radiation characteristics and enhancement of wireless systems through antenna coding. This work proposes a novel deep learning-based antenna coding optimization algorithm. Specifically, the proposed algorithm is supported by a heterogeneous multi-head selection mechanism, whose main idea is to train multiple neural networks based on various coding schemes and select the one that leads to the best system performance. Unlike traditional heuristic searching- based algorithms that require high computational complexity to achieve satisfactory performance, the proposed data-driven deep learning approach can achieve 98% of the performance achieved by the searching-based algorithms with significantly reduced computational complexity. Results demonstrate that in pixel antenna empowered single-input single-output systems, the proposed algorithm achieves a computational speed 81 times faster than the searching-based algorithm. For more complex pixel antenna empowered multiple-input multiple-output systems, the computational speed is 297 times faster than the existing searching-based algorithm. Benefiting from the high performance and low computational complexity, this algorithm demonstrates the significant potential of pixel antennas as a novel and practical technology to enhance wireless systems. Index Terms—Antenna coding, deep learning, heterogeneous multi-head selection, neural networks, pixel antennas.",
  "sections": [
    {
      "section_id": "1",
      "original_section_number": "I",
      "section_title": "INTRODUCTION",
      "level": 1,
      "text": " Antennas are pivotal components in wireless communi- cation systems. The multiple-input multiple-output (MIMO) technology enabled by multiple antennas has provided mile- stone advancements from 3G to 5G and is expected to remain dominant in the upcoming 6G networks [1]. While increasing the scale of MIMO is able to reach higher requirements in throughput, latency, and coverage for 6G networks, it may not always be a good choice due to the significantly increased complexity of signal processing, hardware com- plexity, and cost [2]. Instead, exploring the new degrees of freedom provided by antennas themselves, by reconfiguring the antenna characteristics, is envisioned to enhance the 6G communication network. Antennas in conventional MIMO systems typically have fixed configuration and characteristics, such as operating † Corresponding author. frequency, radiation pattern, and polarization, meaning that antennas are excluded from signal processing and system optimization, yielding limited performance. To overcome this limitation, pixel antennas, as a reconfigurable antenna technol- ogy, are a promising solution. Pixel antennas are constructed by discretizing the radiation surface into a small grid of pixels and interconnecting them with RF switches [3]. By controlling the states of RF switches, the antenna topology and configuration can be adjusted to reconfigure the character- istics [4]–[6]. Related to pixel antennas, there is an emerging technology called fluid antenna systems (FAS) [7], where the antenna can switch position within a linear region. This position-switchable capability enables FAS to adapt to channel by adjusting the position, so as to enhance performance in various applications, such as reducing outage probability [8] and enhancing multiple access [9]. Pixel antennas have been adopted to mimic the antenna movement of FAS by controlling states of RF switches [10], which preliminarily reveals the potential of pixel antennas in wireless systems. To further leverage the advantages of pixel antennas, a promising technique called antenna coding has been recently proposed for pixel antenna empowered wireless systems [11]. In antenna coding, the RF switch states are represented by binary variables called antenna coder, which can be optimized to adapt to the channel and enhance the wireless system. To optimize antenna coding for pixel antenna empowered systems, heuristic searching-based algorithms are utilized [11], [12], which rely on exhaustive searching over a large range. Therefore, it poses a critical challenge to balance the perfor- mance and computational complexity. To overcome this challenge, in this work, we propose a deep learning-based antenna coding optimization algorithm using a heterogeneous multi-head selection mechanism (HMSM). Deep learning [13], as a data-driven approach, is renowned for efficient computation and high accuracy in complex problems, offering a promising method to achieve a better performance- complexity tradeoff. Specifically, the proposed algorithm with HMSM is inspired by the multi-head attention mechanism for dealing with highly nonlinear problems with enhanced accuracy and robustness [14], and built on the pixel antenna arXiv:2602.23831v1 [cs.IT] 27 Feb 2026 Fig. 1. (a) An example of pixel antenna designs proposed in [3] and (b) the multi-port circuit network for pixel antenna. communication model [11]. Another innovation of the pro- posed algorithm is that it utilizes the binary/Gray coding scheme to compress binary coders into an antenna map in compact decimal format, drastically reducing computational complexity. The efficiency and effectiveness of the proposed algorithm is validated by considering a channel gain max- imization in pixel antenna empowered single-input single- output (SISO) systems, followed by the extension to MIMO capacity maximization. Results show that the proposed algo- rithm achieves 98% of the performance achieved by the heuris- tic searching-based algorithm, while significantly reducing the computational complexity by up to 297 times, demonstrating the benefits of the deep learning-based proposed algorithm. Notations: Boldface lower-case and upper-case letters indi- cate column vectors and matrices, respectively. C and R+ de- note the set of complex and positive real numbers, respectively. (·)∗, (·)T, (·)H, and (·)−1 denote the conjugate, transpose, conjugate-transpose, and inversion operations, respectively. ∥·∥ denotes the ℓ-norm of a vector. |A| denotes the determinant of a matrix A and |a| denotes the absolute value of a scalar a. ℜ{·} and ℑ{·} denote the real and imaginary parts of a matrix, vector, or scalar."
    },
    {
      "section_id": "2",
      "original_section_number": "II",
      "section_title": "ANTENNA CODING BASED ON PIXEL ANTENNA",
      "level": 1,
      "text": " In this section, we introduce the antenna coding technique based on pixel antennas, including the model and optimization formulation."
    },
    {
      "section_id": "3",
      "original_section_number": "A",
      "section_title": "Pixel Antenna Model",
      "level": 1,
      "text": " Pixel antennas are a reconfigurable antenna technology based on a discretized radiating surface embedded with RF switches. As shown in Fig. 1(a), its core principle involves pixelizing a continuous radiating surface into numerous sub- wavelength units called pixels. Adjacent pixels are intercon- nected via RF switches [3]. By controlling the on and off states of these switches, the antenna topology can be dynam- ically reconfigured, enabling real-time control over radiation characteristics such as radiation pattern. Pixel antennas can be modeled using microwave multi-port network theory, as illustrated in Fig. 1(b). A pixel antenna having Q switches is represented as a (Q + 1)-port network, comprising one antenna port and Q pixel ports to model the Q switches. This yields the following expressions for the antenna port voltage vA ∈C and current iA ∈C, and the pixel port voltage vector vP ∈CQ×1 and current vector iP ∈CQ×1 as \u0014vA vP \u0015 = \u0014zAA zAP zPA zPP \u0015 \u0014iA iP \u0015 , (1) where zAA ∈C and ZPP ∈CQ×Q, respectively, describing the self-impedance for the antenna port and pixel ports; zPA ∈CQ×1 and zAP ∈C1×Q, respectively, being the trans- impedance relating the voltage of the antenna port to currents of pixel ports, zPA = zT AP. Among all Q + 1 ports in the network, each of the Q pixel ports is further connected to a load impedance zL,q representing the states of a switch, as shown in Fig. 1(b). For on state the load impedance is short-circuit while for off state the load impedance is open-circuit. We describe the on and off states of each switch using a binary variable bq ∈{0, 1}. This allows the binary vector b = [b1, . . . , bQ]T ∈ {0, 1}Q×1, referred to as the antenna coder. Therefore, the load impedance matrix is a function of the antenna coder given by ZL(b) = diag(zL,1, . . . , zL,Q) ∈CQ×Q with1 zL,q = ( ∞, if bq = 1, 0, if bq = 0. (2) ZL(b) relates the voltage vP and current iP by vP = −ZL(b)iP. As a result, the currents at the pixel ports can be described as iP(b) = −(ZPP + ZL(b))−1zPAiA. (3) To derive the radiation pattern of a pixel antenna as a func- tion of the antenna coder b, we first introduce the open- circuit radiation pattern matrix Eoc = [eoc A , eoc P,1, . . . , eoc P,Q] ∈ C2K×(Q+1), which contains the radiation pattern eoc A ∈ C2K×1 (comprising θ and ϕ polarization components across K spatial samples) excited by a unit current at the antenna port with all other ports open-circuit, and radiation patterns eoc P,q ∈C2K×1 ∀q excited by a unit current at the pixel port q with all other ports open-circuit. Given Eoc, the radiation pattern of the pixel antenna is obtained as the superposition of radiation patterns from all Q + 1 ports, e(b) = Eoci(b), (4) where i(b) = [iA; ip(b)]. By flexibly selecting b within its feasible range, the radiation pattern e(b) of the pixel antenna can be reconfigured, thereby providing additional beam manipulation flexibility to improve wireless systems."
    },
    {
      "section_id": "4",
      "original_section_number": "B",
      "section_title": "Formulation for Antenna Coding Optimization",
      "level": 1,
      "text": " In this work, we consider two typical use cases of pixel antennas, namely pixel antenna empowered SISO and MIMO systems, as shown in Fig. 2 and explained in the sequel. Case 1: Pixel Antenna Empowered SISO System. A pixel antenna empowered SISO system is first considered where 1The open-circuit state of the switch is numerically approximated as zL,q = ȷγ, where ȷ denotes the imaginary unit and γ ∈R+ is sufficiently large, such as γ = 1010. Fig. 2. Diagram of (a) pixel antenna empowered SISO systems and (b) pixel antenna empowered MIMO systems integrated with HMSM. the transmitter is equipped with a conventional antenna with fixed configurations and the receiver is equipped with a pixel antenna, as illustrated in Fig. 2(a). This is the simplest case utilizing pixel antennas. To explicitly characterize the impact of antenna coding using single pixel antenna on channel gain performance, we consider the beamspace channel expression [11], [15], i.e. h(bR) = eT R(bR)HveT, (5) where eR(bR) is the normalized radiation pattern of the pixel antenna at the receiver coded by antenna coder bR with ∥eR(bR)∥= 1 and eT is the normalized radiation pattern of the conventional antenna with fixed configuration at the transmitter satisfying ∥eT∥= 1. Meanwhile, Hv ∈C2K×2K denotes a virtual channel and can be written as Hv = \u0014 Hv,θθ Hv,θϕ Hv,ϕθ Hv,ϕϕ \u0015 , (6) where Hv,θθ, Hv,θϕ, Hv,ϕθ, Hv,ϕϕ ∈CK×K represent the virtual channel matrices for θ and ϕ polarizations, respectively, with each entry denoting the channel gain from an angle of departure (AoD) to an angle of arrival (AoA) across K spatial angle samples2. Aiming at maximizing the channel gain performance, the antenna coder design problem can be formulated as3 max bR |eT R(bR)HveT|2, s.t. [bR]q ∈{0, 1}, ∀q. (7) Case 2: Pixel Antenna Empowered MIMO System. We next consider a MIMO system, as illustrated in Fig. 2(b), where the transmitter (receiver) is equipped with NT (NR) pixel antennas, each of which is coded by the antenna coder bT,nT (bR,nR). The transmit and receive antenna coders are 2In this work, we consider a rich scattering environment with Rayleigh fading, assuming [Hv]i,j ∀i, j are independent and identically distributed random variables following a complex Gaussian distribution. 3The current at the antenna port of the pixel antenna, denoted as iR A, should be a variable to ensure the radiation pattern satisfies that ∥eR(bR)∥= 1. However, it can be removed since iR A is essentially a function of bR so that the antenna coder is the only variable in the channel gain maximization problem. collected into matrices BT = [bT,1, . . . , bT,NT] ∈RQ×NT and BR = [bR,1, . . . , bR,NR] ∈RQ×NR. We formulate the beamspace channel representation for the pixel antenna empowered MIMO system, H(BT, BR) ∈CNR×NT, as H(BT, BR) = ET R(BR)HvET(BT), (8) where ET(BT) = [eT,1(bT,1), . . . , eT,NT(bT,NT)] ∈ C2K×NT with eT,nT(bT,nT) being the normalized radiation pattern of the nTth transmit pixel antenna satisfying ∥eT,nT(bT,nT)∥ = 1, and ER(BR) = [eR,1(bR,1), . . . , eR,NR(bR,NR)] ∈ C2K×NR with eR,nR(bR,nR) being the normalized radiation pattern of the nRth receive pixel antenna satisfying ∥eR,nR(bR,nR)∥= 1. Aiming at maximizing the channel capacity and assuming uniform power allocation at the transmitter, the antenna coder optimization problem can be formulated as max BT,BR log2 I + P σ2NT H(BT, BR)HH(BT, BR) s.t. [BT]i,j ∈{0, 1}, ∀i, j, [BR]i,j ∈{0, 1}, ∀i, j. (9) where I denotes the identity matrix with a proper dimension, σ2 represents the power of additive white Gaussian noise, and P is the transmit power. In this case, we define the signal-to- noise ratio (SNR) as P σ2 . While the above two antenna coding optimization problems (7) and (9), as binary optimization problems, have been solved by some heuristic searching-based algorithms, such as successive exhaustive Boolean optimization (SEBO) [16], the satisfactory performance is achieved at the cost of high compu- tational complexity. To reduce the computational complexity for antenna coding optimization, in the following section, we will propose a deep learning-based algorithm for both pixel antenna empowered SISO and MIMO systems."
    },
    {
      "section_id": "5",
      "original_section_number": "III",
      "section_title": "DEEP LEARNING-BASED ANTENNA CODING DESIGN",
      "level": 1,
      "text": " In this section, we propose a deep learning-based antenna coding design algorithm supported by the novel HMSM. The proposed HMSM is inspired by the multi-head design whose aim is to enable parallel decoding of the input across multiple independent representation subspaces [17]. From a probabilis- tic perspective, denote the probability that each head correctly produces the output as pi. Then the overall probability of the system accurately producing the correct output given the input, satisfies the following lower bound [18] Pcorrect ≥1 − L Y i=1 (1 −pi) !α , (10) where α is a correlation-dependent parameter and L denotes the number of heads. This lower bound demonstrates that when the error patterns of different heads are uncorrelated (α = 1), multi-head collaboration can significantly enhance system robustness, even when the individual accuracy of each head is relatively low. Below, we will first explain the architecture of HMSM, followed by the whole training process. Fig. 3. (a) Architecture of deep learning-based antenna coding design algorithm. (b) The major components for the model training process, which include the dataset preparation process and the training process. (c) An example of encoding pixel antenna with Q pixel ports into two antenna maps."
    },
    {
      "section_id": "6",
      "original_section_number": "A",
      "section_title": "Architecture of HMSM",
      "level": 1,
      "text": " The proposed HMSM has an architecture comprising three key components: a three-channel input, a heterogeneous multi- head module, and a unzip layer together with a decision function, as shown in Fig. 3(a). 1) Three-Feature Maps Input: In this work, the three- feature maps are adopted, analogous to the RGB input in computer vision [19]. The three-feature maps are constructed as follows: the first two maps are the real and imaginary parts of the virtual channel matrix Hv, i.e., ℜ{Hv} and ℑ{Hv}, respectively. In the case of SISO scenarios, the third map is set as ℜ{Hv}; in the case of MIMO systems, the third map is formed by the element-wise product of the SNR value and the real part, i.e., SNR × ℜ{Hv}. This design serves two key purposes: 1) it ensures all input channels have identical dimensions, which is a requirement for standard convolutional neural network architectures; 2) it provides an explicit inductive bias by fusing the SNR information directly with the channel state information. This allows the network to more efficiently learn features that are conditioned on the SNR level, rather than treating SNR as a separate global variable. 2) Heterogeneous Multi-Head Module: This component consists of multiple ResNet50 convolutional neural networks [19]. Each ResNet50 serves as an individual head, processing the input matrix through pooling and convolution opera- tions. The resulting features are then flattened into vectors and passed through fully connected layers that apply linear transformations for logistic regression. In addtion, each head ultimately outputs the encoded antenna coder (antenna map), the design of which will be detailed in the Training Process section. 3) Unzip Layer and Decision Function: The antenna maps generated by each head are processed through the unzip layer, yielding multiple candidate solutions for the antenna coders bR (or BT and BR). The final output b⋆ R (or B⋆ T and B⋆ R) is then determined by selecting the optimal candidate through a comparative evaluation using the decision func- tion of |eT R(bR)HveT|2 for pixel antenna empowered SISO systems or log2 I + P σ2NT H(BT, BR)HH(BT, BR) for pixel antenna empowered MIMO systems."
    },
    {
      "section_id": "7",
      "original_section_number": "B",
      "section_title": "Training Process",
      "level": 1,
      "text": " The training process consists of the following steps. Step 1: The training begins with the preparation of the dataset, as illustrated in Fig. 3(b). ℜ{Hv}, ℑ{Hv}, and SNR serve as training data, while the corresponding optimal antenna coder b⋆ R (or B⋆ T and B⋆ R) is generated by optimizing the antenna coder through the SEBO algorithm. Step 2: The antenna coders are further used to generate antenna maps, referred to as a reformulation of antenna coders via different encoding schemes. These antenna maps serve as different sets of labels for training different heads to achieve a lower α, as depicted in Fig. 3(b). In order to improve the computational accuracy, we employ L = 2 heads in the considered systems, which necessitates the use of two different encoding schemes. Specifically, every M binary digits in an antenna coder with Q binary entries are encoded into decimal numbers using both binary and Gray coding schemes, pro- ducing lower-dimensional antenna maps that serve as training labels as depicted in Fig. 3(c). Step 3: The deep learning model is trained on an extensive set of labeled samples. The differences between predictions and labels are utilized to provide feedback for model refine- ment over multiple rounds of training, leading to an accurate computational framework. After sufficient training, the well-trained deep learning model can efficiently design high-performance antenna maps that enhance channel gain for pixel antenna empowered SISO systems or capacity for MIMO systems. Computational Complexity: The computational complexity of the neural network is governed by 1) f( Q M ) that represents the model complexity associated with the number of subtasks, i.e., Q M and 2) g(2M) that denotes the learning burden intro- duced by the classification freedom of each subtask. Both are increasing functions. The overall complexity is given by [20] D(M) = Φ \u0012 f \u0012 Q M \u0013 , g(2M) \u0013 , (11) where Φ(·) is a combination function describing how f(·) and g(·) collectively determine the total difficulty. When M keeps increasing while remaining relatively small, the reduction of the number of subtasks Q M will lead to the reduction of the total complexity. However, when M becomes excessively large, the exponential growth in the number of categories per subtask 2M becomes the dominant factor, leading to increasing overall complexity. Therefore, it is important to properly choose the value of M based on a given Q. Remark: The distinction between the two cases lies solely in the label acquisition process. In the SISO case, the labels correspond to the optimal antenna coder b⋆that maximizes the channel gain and are obtained using the SEBO algorithm. In contrast, for the MIMO case, the labels are the optimal antenna coders B⋆ T and B⋆ R that maximize the channel capacity, which are obtained using the SEBO algorithm assuming the transmitter performs a uniform power allocation [11]."
    },
    {
      "section_id": "8",
      "original_section_number": "IV",
      "section_title": "PERFORMANCE EVALUATION",
      "level": 1,
      "text": " We consider a rich scattering propagation environment where each entry in the virtual channel Hv are independently and identically complex Gaussian distributed random vari- ables. The angular resolution is set to ∆ϕ = 5◦, resulting in K = 72 angular samples. For the pixel antenna empowered SISO system, the transmit antenna is assumed to have a fixed isotropic radiation pattern, while the receive antenna is a pixel antenna. For the pixel antenna empowered MIMO system, 4 transmit and 2 receive pixel antennas are assumed. Following [11], each pixel antenna has a physical aperture of 0.5λ×0.5λ, where λ = 125 mm denotes the wavelength, and Q = 39 pixel ports. The impedance matrix Z ∈C(Q+1)×(Q+1) and the open-circuit radiation pattern Eoc ∈C2K×(Q+1) are obtained by the CST studio suite. In the following experiments, each pixel antenna is equipped with an HMSM for efficient and effective antenna coding design. We select the number encoded binary digits M = 3 to achieve a good balance between the performance and computational complexity. A dataset of 90,000 unique channel samples is created, with 90% used for training and 10% for testing. The SEBO [16] is used with a block size of 12 to maximize the channel gain and capacity and to prepare for the training data. Fig. 4 evaluates the feasibility and scalability of the deep learning model using either single-head or multi-head mech- Fig. 4. Evaluation of the regression performance of the deep learning model for (a) binary code, (b) Gray code, (c) performance improvement of HMSM, and (d) learning accuracy versus number of samples in the dataset. anisms. Figs. 4(a) and (b) compare deep learning (marked as “DL”) based antenna maps using binary and Gray coding against the ideal maps obtained by the SEBO algorithm (marked as “Searching-based”). To quantitatively evaluate the accuracy of a single head, an element-wise4 comparison between the antenna map generated by two algorithms is performed. For the case of M = 3, each element is a discrete category within the set {0, 1, . . . , 7}, which is treated as an 8-class classification problem. The performance is analyzed by constructing a confusion matrix, which reveals specific element-wise confusion patterns and prediction accuracy of the trained model. The results show that the neural network effectively captures the nonlinear mapping between Hv and the antenna coder, achieving an average accuracy of 97.32%. Furthermore, using the SISO gain achieved by the SEBO algorithm as a benchmark, 1000 Monte Carlo samples are performed. Cumulative channel gains are normalized to quan- tify the performance improvement of the proposed HMSM compared to the single-head scheme using binary or Gray coding. As shown in Fig. 4(c), HMSM significantly improves the performance by selecting the optimal output from multiple heads with different coding schemes, consistent with expec- tations. In particular, due to the strong nonlinear relationship between the channel and the antenna coder, the performance of the proposed algorithm is highly dependent on the size of the dataset. As illustrated in Fig. 4(d), the model exhibits stronger generalization capability when the dataset approaches the order of 105 samples. In Fig. 5, we evaluate the performance of the proposed HMSM in terms of SISO gain, MIMO capacity, and com- putational complexity. Fig. 5(a) compares the performance of 1) the single-head deep learning algorithm (marked as “DL B” and “DL G” for two coding schemes) and 2) the HMSM-enabled deep learning algorithm with existing meth- 4Each “element” refers to one decimal number encoded from M = 3 binary entries in an antenna coder. Fig. 5. Performance comparison of different algorithms under (a) SISO and (b) MIMO systems, and (c) computational time consumption comparison between the HMSM algorithm and searching-based algorithms. ods in the SISO system, including the 1) conventional antenna systems (marked as “Conv”), 2) codebook-based algorithm [11] (marked as “Codebook” with a codebook size of 1024), 3) and the SEBO [16]. We observe from Figs. 5(a) and (c) that, the single-head deep learning algorithms outperform the codebook-based algorithm with much reduced computational complexity. The HMSM further improves the average gain by approximately 17% compared to the single-head deep learning algorithm with slightly higher computational complexity. The performance is only marginally lower than the SEBO algo- rithm. In the MIMO model, as described in Fig. 5(b), using HMSM to design the antenna coder also significantly improves channel capacity, achieving around 98.5% performance of the SEBO algorithm based on uniform power allocation at the transmitter (marked as “UP”). As shown in Fig. 5(c), the time consumption for SISO and MIMO systems using HMSM drastically decreases by 98.77% and 99.66%, respectively. In practical experiments, computing multiple models in parallel effectively mitigates the increasing computational time asso- ciated with higher computational loads in MIMO systems."
    },
    {
      "section_id": "9",
      "original_section_number": "V",
      "section_title": "CONCLUSION",
      "level": 1,
      "text": " This study develops a deep learning-based antenna coding design algorithm for pixel antenna systems. By utilizing a novel HMSM based on multiple coding schemes, the deep learning-based algorithm achieves satisfactory performance in pixel antenna empowered SISO and MIMO systems with sig- nificantly reduced computational complexity. The performance evaluation in SISO systems demonstrates that the proposed algorithm achieves an average channel gain that is of 98.5% of the searching-based benchmark, while the computational time is only 1.23% of the searching-based benchmark. In MIMO systems with multiple transceiver antennas, the pro- posed algorithm achieves an average channel capacity that is 98% of the searching-based algorithm, while further reducing the computation time to merely 0.34% of that required by the searching-based algorithm. Both results demonstrate the benefits of the proposed deep learning-based algorithm."
    },
    {
      "section_id": "10",
      "original_section_number": "",
      "section_title": "ACKNOWLEDGMENT",
      "level": 1,
      "text": " The authors would like to acknowledge the support by the Science and Technology Development Fund, Macau SAR (File/Project no.001/2024/SKL), by University of Macau (File no. SRG2025-00060-IOTSC), and by University of Macau Development Foundation (UMDF) (File no. UMDF-TISF- I/2026/025/IOTSC)."
    },
    {
      "section_id": "11",
      "original_section_number": "",
      "section_title": "REFERENCES",
      "level": 1,
      "text": " [1] S. Yang and L. Hanzo, “Fifty years of MIMO detection: The road to large-scale MIMOs,” IEEE Commun. Surveys & Tuts, vol. 17, no. 4, pp. 1941–1988, 2015. [2] Z. Wang, J. Zhang, H. Du, D. Niyato, S. Cui, B. Ai, M. Debbah, K. B. Letaief, and H. V. Poor, “A tutorial on extremely large-scale MIMO for 6G: Fundamentals, signal processing, and applications,” IEEE Commun. Surveys & Tuts., vol. 26, no. 3, pp. 1560–1605, 2024. [3] Y. Zhang, S. Tang, Z. Han, J. Rao, S. Shen, M. Li, C.-Y. Chiu, and R. Murch, “A low-profile microstrip vertically polarized endfire antenna with 360° beam-scanning and high beam-shaping capability,” IEEE Trans. Antennas Propag., vol. 70, no. 9, pp. 7691–7702, 2022. [4] S. Song and R. D. Murch, “An efficient approach for optimizing frequency reconfigurable pixel antennas using genetic algorithms,” IEEE Trans. Antennas Propag., vol. 62, no. 2, pp. 609–620, 2013. [5] Y. Zhang, Z. Han, S. Tang, S. Shen, C.-Y. Chiu, and R. Murch, “A highly pattern-reconfigurable planar antenna with 360° single-and multi-beam steering,” IEEE Trans. Antennas Propag., vol. 70, no. 8, pp. 6490–6504, 2022. [6] Y. Zhang, Z. Han, S. Shen, C.-Y. Chiu, and R. Murch, “Polarization enhancement of microstrip antennas by asymmetric and symmetric grid defected ground structures,” IEEE Open J. Antennas Propag., vol. 1, pp. 215–223, 2020. [7] K. K. Wong, A. Shojaeifard, K.-F. Tong, and Y. Zhang, “Performance limits of fluid antenna systems,” IEEE Commun. Lett., vol. 24, no. 11, pp. 2469–2472, 2020. [8] L. Zhu, W. Ma, and R. Zhang, “Modeling and performance analysis for movable antenna enabled wireless communications,” IEEE Trans. Wireless Commun., vol. 23, no. 6, pp. 6234–6250, 2024. [9] W. K. New, K.-K. Wong, H. Xu, K.-F. Tong, and C.-B. Chae, “An information-theoretic characterization of MIMO-FAS: Optimization, diversity-multiplexing tradeoff and q-outage capacity,” IEEE Trans. Wireless Commun., vol. 23, no. 6, pp. 5541–5556, 2023. [10] J. Zhang, J. Rao, Z. Li, Z. Ming, C.-Y. Chiu, K.-K. Wong, K.-F. Tong, and R. Murch, “A novel pixel-based reconfigurable antenna applied in fluid antenna systems with high switching speed,” IEEE Open J. Antennas Propag., vol. 6, no. 1, pp. 212–228, 2025. [11] S. Shen, K.-K. Wong, and R. Murch, “Antenna coding empowered by pixel antennas,” IEEE Trans. Commun., 2025. [12] H. Li and S. Shen, “Antenna coding design based on pixel antennas for multi-user MISO systems,” in Proc. IEEE Int. Workshop Signal Process. Artificial Intelligence for Wireless Commun. (SPAWC), 2025, pp. 1–5. [13] R. Van Noorden and J. M. Perkel, “AI and science: what 1,600 researchers think,” Nature, vol. 621, no. 7980, pp. 672–675, 2023. [14] J. Li, X. Wang, Z. Tu, and M. R. Lyu, “On the diversity of multi-head attention,” Neurocomputing, vol. 454, pp. 14–24, 2021. [15] Z. Han, S. Shen, and R. Murch, “Exploiting spatial multiplexing based on pixel antennas: An antenna coding approach,” IEEE J. Sel. Topics Signal Process., 2026. [16] S. Shen, Y. Sun, S. Song, D. P. Palomar, and R. D. Murch, “Successive boolean optimization of planar pixel antennas,” IEEE Trans. Antennas Propag., vol. 65, no. 2, pp. 920–925, 2016. [17] A. Vaswani, N. Shazeer, N. Parmar, J. Uszkoreit, L. Jones, A. N. Gomez, Ł. Kaiser, and I. Polosukhin, “Attention is all you need,” Advances Neural Info. Process. Systs., vol. 30, 2017. [18] D. Bertsekas and J. N. Tsitsiklis, Introduction to probability. Athena Scientific, 2008. [19] B. Koonce, “Resnet 50,” in Convolutional neural networks with swift for tensorflow: image recognition and dataset categorization. Springer, 2021, pp. 63–72. [20] J. Andreas, M. Rohrbach, T. Darrell, and D. Klein, “Neural module net- works,” in Proc. IEEE Conf. Computer Vision and Pattern Recognition, 2016, pp. 39–48."
    }
  ]
}